vaultic/__init__.py
vaultic/app.py
vaultic/meme.py
vaultic/screens.py
vaultic/stego.py
vaultic/styles.tcss
vaultic/vault.py
vaultic-0.1.1.dist-info/METADATA
vaultic-0.1.1.dist-info/WHEEL
vaultic-0.1.1.dist-info/entry_points.txt
vaultic-0.1.1.dist-info/RECORD
