Metadata-Version: 2.4
Name: vaultic
Version: 0.1.1
Summary: Terminal vault using meme steganography
License: MIT
Requires-Python: >=3.10
Requires-Dist: cryptography
Requires-Dist: pillow
Requires-Dist: pyperclip
Requires-Dist: requests
Requires-Dist: rich-pixels
Requires-Dist: textual
